MANIFEST.in
setup.cfg
setup.py
bfcli/COMMAND
bfcli/VERSION
bfcli/__init__.py
bfcli/command.py
bfcli/version.py
bfcli.egg-info/PKG-INFO
bfcli.egg-info/SOURCES.txt
bfcli.egg-info/dependency_links.txt
bfcli.egg-info/entry_points.txt
bfcli.egg-info/requires.txt
bfcli.egg-info/top_level.txt
bfcli/cli/__init__.py
bfcli/cli/config.py
bfcli/cli/data.py
bfcli/cli/environment.py
bfcli/cli/job.py
bfcli/cli/node.py
bfcli/cli/project.py
bfcli/cli/resource.py
bfcli/cli/volume.py
bfcli/cli/workspace.py
bfcli/config/__init__.py
bfcli/config/local_file.py
bfcli/lib/__init__.py
bfcli/lib/analytics.py
bfcli/lib/api.py
bfcli/lib/cli_common.py
bfcli/lib/environments.py
bfcli/lib/local_project.py
bfcli/lib/user.py