Metadata-Version: 1.0
Name: bfcli
Version: 1.0.2
Summary: CLI for interactive with the Bitfusion Platform
Home-page: http://www.bitfusion.io
Author: Brian Schultz
Author-email: brian@bitfusion.io
License: UNKNOWN
Platform: UNKNOWN
